{"id": "5361d2a9-9d84-4e8f-9dd9-cee3b70448ac", "detail": {"findings": [{"AwsAccountId": "123456789012", "CreatedAt": "2025-11-08T04:28:16.897452Z", "UpdatedAt": "2025-11-08T18:28:16.897452Z", "Description": "The S3 bucket does not have public access block settings enabled. This could allow unintended public access to bucket contents.", "ProductArn": "arn:aws:securityhub:ap-southeast-1::product/aws/securityhub", "GeneratorId": "aws-foundational-security-best-practices/v/1.0.0/S3.8", "Region": "us-west-2", "Compliance": {"status": "NON_COMPLIANT"}, "Workflow": {"status": "NOTIFIED"}, "Types": ["Software and Configuration Checks/Industry and Regulatory Standards/AWS-Foundational-Security-Best-Practices"], "Title": "S3 bucket does not have public access blocks configured", "Severity": {"Label": "HIGH"}, "Resources": [{"Id": "arn:aws:s3:::dev-uploads-bucket-7849", "Type": "AwsS3Bucket"}]}]}}
{"id": "84306fff-47dd-44cc-b20e-a0ec1a7d5693", "detail": {"findings": [{"AwsAccountId": "123456789012", "CreatedAt": "2025-11-08T04:28:16.897873Z", "UpdatedAt": "2025-11-09T10:28:16.897873Z", "Description": "GuardDuty detected EC2 instance communicating with a known malicious IP address.", "ProductArn": "arn:aws:securityhub:eu-west-1::product/aws/securityhub", "GeneratorId": "aws/guardduty", "Region": "us-east-1", "Compliance": {"status": "WARNING"}, "Workflow": {"status": "SUPPRESSED"}, "Types": ["TTPs/Command and Control/Backdoor:EC2-C&CActivity.B!DNS"], "Title": "EC2 instance is communicating with known malicious IP", "Severity": {"Label": "HIGH"}, "Resources": [{"Id": "arn:aws:ec2:eu-west-1:456789012345:instance/i-afd969a4a69a4a839", "Type": "AwsEc2Instance"}]}]}}
{"id": "5245723a-042d-4f40-b8d3-ecb440cf3134", "detail": {"findings": [{"AwsAccountId": "987654321098", "CreatedAt": "2025-11-08T04:28:16.897887Z", "UpdatedAt": "2025-11-10T03:28:16.897887Z", "Description": "GuardDuty detected an unusual API call pattern that deviates from baseline behavior.", "ProductArn": "arn:aws:securityhub:us-east-1::product/aws/securityhub", "GeneratorId": "aws/guardduty", "Region": "us-west-2", "Compliance": {"status": "WARNING"}, "Workflow": {"status": "NOTIFIED"}, "Types": ["TTPs/Discovery/Recon:IAMUser-UnusualBehavior"], "Title": "Unusual API call detected", "Severity": {"Label": "MEDIUM"}, "Resources": [{"Id": "arn:aws:ec2:eu-west-1:123456789012:instance/i-8215d56d64ce46efb", "Type": "AwsEc2Instance"}]}]}}
{"id": "6d8601f9-6769-4c74-bc32-2ae17609674d", "detail": {"findings": [{"AwsAccountId": "987654321098", "CreatedAt": "2025-11-08T04:28:16.898004Z", "UpdatedAt": "2025-11-09T18:28:16.898004Z", "Description": "KMS customer-managed keys should have automatic key rotation enabled.", "ProductArn": "arn:aws:securityhub:eu-west-1::product/aws/securityhub", "GeneratorId": "aws-foundational-security-best-practices/v/1.0.0/KMS.4", "Region": "eu-west-1", "Compliance": {"status": "NON_COMPLIANT"}, "Workflow": {"status": "NEW"}, "Types": ["Software and Configuration Checks/Industry and Regulatory Standards/AWS-Foundational-Security-Best-Practices"], "Title": "KMS key rotation is not enabled", "Severity": {"Label": "MEDIUM"}, "Resources": [{"Id": "arn:aws:kms:us-east-1:987654321098:key/7c30f0a9-334b-4611-b420-005f9dcf8869", "Type": "AwsKmsKey"}]}]}}
